diracx/logic/__init__.py
diracx/logic/__main__.py
diracx/logic/py.typed
diracx/logic/auth/__init__.py
diracx/logic/auth/authorize_code_flow.py
diracx/logic/auth/device_flow.py
diracx/logic/auth/management.py
diracx/logic/auth/token.py
diracx/logic/auth/utils.py
diracx/logic/auth/well_known.py
diracx/logic/jobs/__init__.py
diracx/logic/jobs/query.py
diracx/logic/jobs/sandboxes.py
diracx/logic/jobs/status.py
diracx/logic/jobs/submission.py
diracx/logic/jobs/utils.py
diracx/logic/task_queues/__init__.py
diracx/logic/task_queues/priority.py
diracx_logic-0.0.7.dist-info/METADATA
diracx_logic-0.0.7.dist-info/WHEEL
diracx_logic-0.0.7.dist-info/RECORD
