Metadata-Version: 2.4
Name: diracx-logic
Version: 0.0.7
Summary: TODO
License: GPL-3.0-only
Classifier: Intended Audience :: Science/Research
Classifier: License :: OSI Approved :: GNU General Public License v3 (GPLv3)
Classifier: Programming Language :: Python :: 3
Classifier: Topic :: Scientific/Engineering
Classifier: Topic :: System :: Distributed Computing
Requires-Python: >=3.11
Requires-Dist: cachetools
Requires-Dist: diraccommon>=9.0.0
Requires-Dist: diracx-core
Requires-Dist: diracx-db
Requires-Dist: joserfc
Requires-Dist: pydantic>=2.10
Requires-Dist: uuid-utils
Provides-Extra: testing
Requires-Dist: diracx-testing; extra == 'testing'
Requires-Dist: freezegun; extra == 'testing'
Provides-Extra: types
Requires-Dist: types-cachetools; extra == 'types'
